microjs/__init__.py
microjs/ast_nodes.py
microjs/compiler.py
microjs/context.py
microjs/errors.py
microjs/lexer.py
microjs/opcodes.py
microjs/parser.py
microjs/py.typed
microjs/regex/__init__.py
microjs/regex/compiler.py
microjs/regex/opcodes.py
microjs/regex/parser.py
microjs/regex/regex.py
microjs/regex/vm.py
microjs/tokens.py
microjs/values.py
microjs/vm.py
micro_javascript-0.1a3.dist-info/WHEEL
micro_javascript-0.1a3.dist-info/METADATA
micro_javascript-0.1a3.dist-info/RECORD
