Metadata-Version: 2.4
Name: micro-javascript
Version: 0.1a3
Summary: A pure Python JavaScript sandbox engine based on MQuickJS
Author: Simon Willison
License-Expression: MIT
Requires-Python: >=3.10
Project-URL: CI, https://github.com/simonw/micro-javascript/actions
Project-URL: Changelog, https://github.com/simonw/micro-javascript/releases
Project-URL: Homepage, https://github.com/simonw/micro-javascript
Project-URL: Issues, https://github.com/simonw/micro-javascript/issues
